jow_api/__init__.py
jow_api-0.1.4.dist-info/LICENSE
jow_api-0.1.4.dist-info/METADATA
jow_api-0.1.4.dist-info/WHEEL
jow_api-0.1.4.dist-info/top_level.txt
jow_api-0.1.4.dist-info/RECORD
