Metadata-Version: 2.1
Name: jow-api
Version: 0.1.4
Summary: Simple Python API for Jow.fr
Home-page: https://github.com/NolanO64/python-jow-api
Author: Nolan Otam
License: MIT
License-File: LICENSE
Requires-Dist: requests
